{
  "hunt": "faction_floor",
  "config": {
    "baseSeed": 111006,
    "gamesPerGridConfig": 300,
    "gamesPerExtremeField": 1000,
    "gridConfigs": 80,
    "fields": [
      "mixed",
      "allRusher",
      "allTrader",
      "allOpportunist"
    ],
    "smoke": false,
    "elapsedMs": 89928,
    "thresholds": {
      "floor": 0.05,
      "ceiling": 0.55,
      "medianMin": 9,
      "capCloseMax": 0.4
    }
  },
  "grid": {
    "byzantium": {
      "rusher": {
        "mixed": {
          "focalFaction": "byzantium",
          "focalPolicy": "rusher",
          "field": "mixed",
          "games": 300,
          "firstSeed": 256702427,
          "focalWins": 38,
          "focalWinRate": 0.12666666666666668,
          "focalEliminated": 0,
          "focalElimRate": 0,
          "victoryTypes": {
            "threshold": 148,
            "cap": 126,
            "suddenDeath": 26,
            "elimination": 0
          },
          "medianRounds": 16,
          "meanRounds": 15.256666666666666,
          "capCloseMargin": 22,
          "capCloseMarginRate": 0.07333333333333333,
          "focalWinTypes": {
            "threshold": 32,
            "cap": 6,
            "suddenDeath": 0,
            "elimination": 0
          }
        },
        "allRusher": {
          "focalFaction": "byzantium",
          "focalPolicy": "rusher",
          "field": "allRusher",
          "games": 300,
          "firstSeed": 391196674,
          "focalWins": 35,
          "focalWinRate": 0.11666666666666667,
          "focalEliminated": 0,
          "focalElimRate": 0,
          "victoryTypes": {
            "threshold": 90,
            "cap": 156,
            "suddenDeath": 54,
            "elimination": 0
          },
          "medianRounds": 16,
          "meanRounds": 15.276666666666667,
          "capCloseMargin": 23,
          "capCloseMarginRate": 0.07666666666666666,
          "focalWinTypes": {
            "threshold": 29,
            "cap": 6,
            "suddenDeath": 0,
            "elimination": 0
          }
        },
        "allTrader": {
          "focalFaction": "byzantium",
          "focalPolicy": "rusher",
          "field": "allTrader",
          "games": 300,
          "firstSeed": 1740232575,
          "focalWins": 50,
          "focalWinRate": 0.16666666666666666,
          "focalEliminated": 0,
          "focalElimRate": 0,
          "victoryTypes": {
            "threshold": 281,
            "cap": 15,
            "suddenDeath": 4,
            "elimination": 0
          },
          "medianRounds": 16,
          "meanRounds": 15.303333333333333,
          "capCloseMargin": 6,
          "capCloseMarginRate": 0.02,
          "focalWinTypes": {
            "threshold": 50,
            "cap": 0,
            "suddenDeath": 0,
            "elimination": 0
          }
        },
        "allOpportunist": {
          "focalFaction": "byzantium",
          "focalPolicy": "rusher",
          "field": "allOpportunist",
          "games": 300,
          "firstSeed": 396049228,
          "focalWins": 40,
          "focalWinRate": 0.13333333333333333,
          "focalEliminated": 0,
          "focalElimRate": 0,
          "victoryTypes": {
            "threshold": 160,
            "cap": 87,
            "suddenDeath": 53,
            "elimination": 0
          },
          "medianRounds": 16,
          "meanRounds": 14.946666666666667,
          "capCloseMargin": 6,
          "capCloseMarginRate": 0.02,
          "focalWinTypes": {
            "threshold": 38,
            "cap": 2,
            "suddenDeath": 0,
            "elimination": 0
          }
        }
      },
      "trader": {
        "mixed": {
          "focalFaction": "byzantium",
          "focalPolicy": "trader",
          "field": "mixed",
          "games": 300,
          "firstSeed": 810716578,
          "focalWins": 56,
          "focalWinRate": 0.18666666666666668,
          "focalEliminated": 0,
          "focalElimRate": 0,
          "victoryTypes": {
            "threshold": 159,
            "cap": 123,
            "suddenDeath": 18,
            "elimination": 0
          },
          "medianRounds": 16,
          "meanRounds": 15.376666666666667,
          "capCloseMargin": 16,
          "capCloseMarginRate": 0.05333333333333334,
          "focalWinTypes": {
            "threshold": 31,
            "cap": 25,
            "suddenDeath": 0,
            "elimination": 0
          }
        },
        "allRusher": {
          "focalFaction": "byzantium",
          "focalPolicy": "trader",
          "field": "allRusher",
          "games": 300,
          "firstSeed": 1772428625,
          "focalWins": 58,
          "focalWinRate": 0.19333333333333333,
          "focalEliminated": 0,
          "focalElimRate": 0,
          "victoryTypes": {
            "threshold": 66,
            "cap": 182,
            "suddenDeath": 52,
            "elimination": 0
          },
          "medianRounds": 16,
          "meanRounds": 15.596666666666666,
          "capCloseMargin": 36,
          "capCloseMarginRate": 0.12,
          "focalWinTypes": {
            "threshold": 19,
            "cap": 39,
            "suddenDeath": 0,
            "elimination": 0
          }
        },
        "allTrader": {
          "focalFaction": "byzantium",
          "focalPolicy": "trader",
          "field": "allTrader",
          "games": 300,
          "firstSeed": 330222387,
          "focalWins": 13,
          "focalWinRate": 0.043333333333333335,
          "focalEliminated": 0,
          "focalElimRate": 0,
          "victoryTypes": {
            "threshold": 291,
            "cap": 9,
            "suddenDeath": 0,
            "elimination": 0
          },
          "medianRounds": 16,
          "meanRounds": 15.436666666666667,
          "capCloseMargin": 8,
          "capCloseMarginRate": 0.02666666666666667,
          "focalWinTypes": {
            "threshold": 13,
            "cap": 0,
            "suddenDeath": 0,
            "elimination": 0
          }
        },
        "allOpportunist": {
          "focalFaction": "byzantium",
          "focalPolicy": "trader",
          "field": "allOpportunist",
          "games": 300,
          "firstSeed": 1073561361,
          "focalWins": 48,
          "focalWinRate": 0.16,
          "focalEliminated": 0,
          "focalElimRate": 0,
          "victoryTypes": {
            "threshold": 152,
            "cap": 117,
            "suddenDeath": 31,
            "elimination": 0
          },
          "medianRounds": 16,
          "meanRounds": 15.106666666666667,
          "capCloseMargin": 8,
          "capCloseMarginRate": 0.02666666666666667,
          "focalWinTypes": {
            "threshold": 31,
            "cap": 17,
            "suddenDeath": 0,
            "elimination": 0
          }
        }
      },
      "turtler": {
        "mixed": {
          "focalFaction": "byzantium",
          "focalPolicy": "turtler",
          "field": "mixed",
          "games": 300,
          "firstSeed": 1707220357,
          "focalWins": 44,
          "focalWinRate": 0.14666666666666667,
          "focalEliminated": 0,
          "focalElimRate": 0,
          "victoryTypes": {
            "threshold": 157,
            "cap": 123,
            "suddenDeath": 20,
            "elimination": 0
          },
          "medianRounds": 16,
          "meanRounds": 15.49,
          "capCloseMargin": 22,
          "capCloseMarginRate": 0.07333333333333333,
          "focalWinTypes": {
            "threshold": 23,
            "cap": 21,
            "suddenDeath": 0,
            "elimination": 0
          }
        },
        "allRusher": {
          "focalFaction": "byzantium",
          "focalPolicy": "turtler",
          "field": "allRusher",
          "games": 300,
          "firstSeed": 2029831106,
          "focalWins": 50,
          "focalWinRate": 0.16666666666666666,
          "focalEliminated": 0,
          "focalElimRate": 0,
          "victoryTypes": {
            "threshold": 56,
            "cap": 203,
            "suddenDeath": 41,
            "elimination": 0
          },
          "medianRounds": 16,
          "meanRounds": 15.723333333333333,
          "capCloseMargin": 35,
          "capCloseMarginRate": 0.11666666666666667,
          "focalWinTypes": {
            "threshold": 10,
            "cap": 40,
            "suddenDeath": 0,
            "elimination": 0
          }
        },
        "allTrader": {
          "focalFaction": "byzantium",
          "focalPolicy": "turtler",
          "field": "allTrader",
          "games": 300,
          "firstSeed": 2142586444,
          "focalWins": 10,
          "focalWinRate": 0.03333333333333333,
          "focalEliminated": 0,
          "focalElimRate": 0,
          "victoryTypes": {
            "threshold": 285,
            "cap": 15,
            "suddenDeath": 0,
            "elimination": 0
          },
          "medianRounds": 16,
          "meanRounds": 15.333333333333334,
          "capCloseMargin": 12,
          "capCloseMarginRate": 0.04,
          "focalWinTypes": {
            "threshold": 10,
            "cap": 0,
            "suddenDeath": 0,
            "elimination": 0
          }
        },
        "allOpportunist": {
          "focalFaction": "byzantium",
          "focalPolicy": "turtler",
          "field": "allOpportunist",
          "games": 300,
          "firstSeed": 1214018418,
          "focalWins": 25,
          "focalWinRate": 0.08333333333333333,
          "focalEliminated": 0,
          "focalElimRate": 0,
          "victoryTypes": {
            "threshold": 134,
            "cap": 138,
            "suddenDeath": 28,
            "elimination": 0
          },
          "medianRounds": 16,
          "meanRounds": 15.463333333333333,
          "capCloseMargin": 11,
          "capCloseMarginRate": 0.03666666666666667,
          "focalWinTypes": {
            "threshold": 6,
            "cap": 19,
            "suddenDeath": 0,
            "elimination": 0
          }
        }
      },
      "opportunist": {
        "mixed": {
          "focalFaction": "byzantium",
          "focalPolicy": "opportunist",
          "field": "mixed",
          "games": 300,
          "firstSeed": 1602774727,
          "focalWins": 123,
          "focalWinRate": 0.41,
          "focalEliminated": 0,
          "focalElimRate": 0,
          "victoryTypes": {
            "threshold": 183,
            "cap": 80,
            "suddenDeath": 37,
            "elimination": 0
          },
          "medianRounds": 16,
          "meanRounds": 15,
          "capCloseMargin": 10,
          "capCloseMarginRate": 0.03333333333333333,
          "focalWinTypes": {
            "threshold": 104,
            "cap": 19,
            "suddenDeath": 0,
            "elimination": 0
          }
        },
        "allRusher": {
          "focalFaction": "byzantium",
          "focalPolicy": "opportunist",
          "field": "allRusher",
          "games": 300,
          "firstSeed": 270542993,
          "focalWins": 56,
          "focalWinRate": 0.18666666666666668,
          "focalEliminated": 0,
          "focalElimRate": 0,
          "victoryTypes": {
            "threshold": 93,
            "cap": 129,
            "suddenDeath": 78,
            "elimination": 0
          },
          "medianRounds": 16,
          "meanRounds": 15.146666666666667,
          "capCloseMargin": 21,
          "capCloseMarginRate": 0.07,
          "focalWinTypes": {
            "threshold": 46,
            "cap": 10,
            "suddenDeath": 0,
            "elimination": 0
          }
        },
        "allTrader": {
          "focalFaction": "byzantium",
          "focalPolicy": "opportunist",
          "field": "allTrader",
          "games": 300,
          "firstSeed": 1083234571,
          "focalWins": 114,
          "focalWinRate": 0.38,
          "focalEliminated": 0,
          "focalElimRate": 0,
          "victoryTypes": {
            "threshold": 291,
            "cap": 7,
            "suddenDeath": 2,
            "elimination": 0
          },
          "medianRounds": 15,
          "meanRounds": 14.896666666666667,
          "capCloseMargin": 2,
          "capCloseMarginRate": 0.006666666666666667,
          "focalWinTypes": {
            "threshold": 114,
            "cap": 0,
            "suddenDeath": 0,
            "elimination": 0
          }
        },
        "allOpportunist": {
          "focalFaction": "byzantium",
          "focalPolicy": "opportunist",
          "field": "allOpportunist",
          "games": 300,
          "firstSeed": 1326860979,
          "focalWins": 49,
          "focalWinRate": 0.16333333333333333,
          "focalEliminated": 0,
          "focalElimRate": 0,
          "victoryTypes": {
            "threshold": 153,
            "cap": 95,
            "suddenDeath": 52,
            "elimination": 0
          },
          "medianRounds": 16,
          "meanRounds": 14.963333333333333,
          "capCloseMargin": 9,
          "capCloseMarginRate": 0.03,
          "focalWinTypes": {
            "threshold": 43,
            "cap": 6,
            "suddenDeath": 0,
            "elimination": 0
          }
        }
      }
    },
    "ottomans": {
      "rusher": {
        "mixed": {
          "focalFaction": "ottomans",
          "focalPolicy": "rusher",
          "field": "mixed",
          "games": 300,
          "firstSeed": 130802393,
          "focalWins": 91,
          "focalWinRate": 0.30333333333333334,
          "focalEliminated": 0,
          "focalElimRate": 0,
          "victoryTypes": {
            "threshold": 140,
            "cap": 114,
            "suddenDeath": 46,
            "elimination": 0
          },
          "medianRounds": 16,
          "meanRounds": 15.416666666666666,
          "capCloseMargin": 18,
          "capCloseMarginRate": 0.06,
          "focalWinTypes": {
            "threshold": 24,
            "cap": 21,
            "suddenDeath": 46,
            "elimination": 0
          }
        },
        "allRusher": {
          "focalFaction": "ottomans",
          "focalPolicy": "rusher",
          "field": "allRusher",
          "games": 300,
          "firstSeed": 1103959080,
          "focalWins": 151,
          "focalWinRate": 0.5033333333333333,
          "focalEliminated": 0,
          "focalElimRate": 0,
          "victoryTypes": {
            "threshold": 74,
            "cap": 159,
            "suddenDeath": 67,
            "elimination": 0
          },
          "medianRounds": 16,
          "meanRounds": 15.45,
          "capCloseMargin": 16,
          "capCloseMarginRate": 0.05333333333333334,
          "focalWinTypes": {
            "threshold": 28,
            "cap": 56,
            "suddenDeath": 67,
            "elimination": 0
          }
        },
        "allTrader": {
          "focalFaction": "ottomans",
          "focalPolicy": "rusher",
          "field": "allTrader",
          "games": 300,
          "firstSeed": 527193960,
          "focalWins": 57,
          "focalWinRate": 0.19,
          "focalEliminated": 0,
          "focalElimRate": 0,
          "victoryTypes": {
            "threshold": 252,
            "cap": 10,
            "suddenDeath": 38,
            "elimination": 0
          },
          "medianRounds": 16,
          "meanRounds": 15.243333333333334,
          "capCloseMargin": 9,
          "capCloseMarginRate": 0.03,
          "focalWinTypes": {
            "threshold": 19,
            "cap": 0,
            "suddenDeath": 38,
            "elimination": 0
          }
        },
        "allOpportunist": {
          "focalFaction": "ottomans",
          "focalPolicy": "rusher",
          "field": "allOpportunist",
          "games": 300,
          "firstSeed": 1707184472,
          "focalWins": 92,
          "focalWinRate": 0.30666666666666664,
          "focalEliminated": 0,
          "focalElimRate": 0,
          "victoryTypes": {
            "threshold": 167,
            "cap": 77,
            "suddenDeath": 56,
            "elimination": 0
          },
          "medianRounds": 16,
          "meanRounds": 15.043333333333333,
          "capCloseMargin": 11,
          "capCloseMarginRate": 0.03666666666666667,
          "focalWinTypes": {
            "threshold": 18,
            "cap": 18,
            "suddenDeath": 56,
            "elimination": 0
          }
        }
      },
      "trader": {
        "mixed": {
          "focalFaction": "ottomans",
          "focalPolicy": "trader",
          "field": "mixed",
          "games": 300,
          "firstSeed": 930740028,
          "focalWins": 4,
          "focalWinRate": 0.013333333333333334,
          "focalEliminated": 0,
          "focalElimRate": 0,
          "victoryTypes": {
            "threshold": 154,
            "cap": 145,
            "suddenDeath": 1,
            "elimination": 0
          },
          "medianRounds": 16,
          "meanRounds": 15.35,
          "capCloseMargin": 35,
          "capCloseMarginRate": 0.11666666666666667,
          "focalWinTypes": {
            "threshold": 1,
            "cap": 2,
            "suddenDeath": 1,
            "elimination": 0
          }
        },
        "allRusher": {
          "focalFaction": "ottomans",
          "focalPolicy": "trader",
          "field": "allRusher",
          "games": 300,
          "firstSeed": 178338621,
          "focalWins": 37,
          "focalWinRate": 0.12333333333333334,
          "focalEliminated": 0,
          "focalElimRate": 0,
          "victoryTypes": {
            "threshold": 90,
            "cap": 205,
            "suddenDeath": 5,
            "elimination": 0
          },
          "medianRounds": 16,
          "meanRounds": 15.336666666666666,
          "capCloseMargin": 26,
          "capCloseMarginRate": 0.08666666666666667,
          "focalWinTypes": {
            "threshold": 7,
            "cap": 25,
            "suddenDeath": 5,
            "elimination": 0
          }
        },
        "allTrader": {
          "focalFaction": "ottomans",
          "focalPolicy": "trader",
          "field": "allTrader",
          "games": 300,
          "firstSeed": 51079364,
          "focalWins": 0,
          "focalWinRate": 0,
          "focalEliminated": 0,
          "focalElimRate": 0,
          "victoryTypes": {
            "threshold": 289,
            "cap": 11,
            "suddenDeath": 0,
            "elimination": 0
          },
          "medianRounds": 16,
          "meanRounds": 15.296666666666667,
          "capCloseMargin": 10,
          "capCloseMarginRate": 0.03333333333333333,
          "focalWinTypes": {
            "threshold": 0,
            "cap": 0,
            "suddenDeath": 0,
            "elimination": 0
          }
        },
        "allOpportunist": {
          "focalFaction": "ottomans",
          "focalPolicy": "trader",
          "field": "allOpportunist",
          "games": 300,
          "firstSeed": 1526025286,
          "focalWins": 11,
          "focalWinRate": 0.03666666666666667,
          "focalEliminated": 0,
          "focalElimRate": 0,
          "victoryTypes": {
            "threshold": 217,
            "cap": 82,
            "suddenDeath": 1,
            "elimination": 0
          },
          "medianRounds": 15,
          "meanRounds": 14.79,
          "capCloseMargin": 10,
          "capCloseMarginRate": 0.03333333333333333,
          "focalWinTypes": {
            "threshold": 3,
            "cap": 7,
            "suddenDeath": 1,
            "elimination": 0
          }
        }
      },
      "turtler": {
        "mixed": {
          "focalFaction": "ottomans",
          "focalPolicy": "turtler",
          "field": "mixed",
          "games": 300,
          "firstSeed": 844283886,
          "focalWins": 0,
          "focalWinRate": 0,
          "focalEliminated": 0,
          "focalElimRate": 0,
          "victoryTypes": {
            "threshold": 184,
            "cap": 116,
            "suddenDeath": 0,
            "elimination": 0
          },
          "medianRounds": 16,
          "meanRounds": 15.283333333333333,
          "capCloseMargin": 17,
          "capCloseMarginRate": 0.056666666666666664,
          "focalWinTypes": {
            "threshold": 0,
            "cap": 0,
            "suddenDeath": 0,
            "elimination": 0
          }
        },
        "allRusher": {
          "focalFaction": "ottomans",
          "focalPolicy": "turtler",
          "field": "allRusher",
          "games": 300,
          "firstSeed": 685128295,
          "focalWins": 0,
          "focalWinRate": 0,
          "focalEliminated": 0,
          "focalElimRate": 0,
          "victoryTypes": {
            "threshold": 71,
            "cap": 229,
            "suddenDeath": 0,
            "elimination": 0
          },
          "medianRounds": 16,
          "meanRounds": 15.47,
          "capCloseMargin": 26,
          "capCloseMarginRate": 0.08666666666666667,
          "focalWinTypes": {
            "threshold": 0,
            "cap": 0,
            "suddenDeath": 0,
            "elimination": 0
          }
        },
        "allTrader": {
          "focalFaction": "ottomans",
          "focalPolicy": "turtler",
          "field": "allTrader",
          "games": 300,
          "firstSeed": 661614920,
          "focalWins": 0,
          "focalWinRate": 0,
          "focalEliminated": 0,
          "focalElimRate": 0,
          "victoryTypes": {
            "threshold": 288,
            "cap": 12,
            "suddenDeath": 0,
            "elimination": 0
          },
          "medianRounds": 16,
          "meanRounds": 15.263333333333334,
          "capCloseMargin": 8,
          "capCloseMarginRate": 0.02666666666666667,
          "focalWinTypes": {
            "threshold": 0,
            "cap": 0,
            "suddenDeath": 0,
            "elimination": 0
          }
        },
        "allOpportunist": {
          "focalFaction": "ottomans",
          "focalPolicy": "turtler",
          "field": "allOpportunist",
          "games": 300,
          "firstSeed": 1924730679,
          "focalWins": 0,
          "focalWinRate": 0,
          "focalEliminated": 0,
          "focalElimRate": 0,
          "victoryTypes": {
            "threshold": 261,
            "cap": 39,
            "suddenDeath": 0,
            "elimination": 0
          },
          "medianRounds": 15,
          "meanRounds": 14.516666666666667,
          "capCloseMargin": 11,
          "capCloseMarginRate": 0.03666666666666667,
          "focalWinTypes": {
            "threshold": 0,
            "cap": 0,
            "suddenDeath": 0,
            "elimination": 0
          }
        }
      },
      "opportunist": {
        "mixed": {
          "focalFaction": "ottomans",
          "focalPolicy": "opportunist",
          "field": "mixed",
          "games": 300,
          "firstSeed": 1838743686,
          "focalWins": 51,
          "focalWinRate": 0.17,
          "focalEliminated": 0,
          "focalElimRate": 0,
          "victoryTypes": {
            "threshold": 156,
            "cap": 103,
            "suddenDeath": 41,
            "elimination": 0
          },
          "medianRounds": 16,
          "meanRounds": 15.266666666666667,
          "capCloseMargin": 14,
          "capCloseMarginRate": 0.04666666666666667,
          "focalWinTypes": {
            "threshold": 8,
            "cap": 2,
            "suddenDeath": 41,
            "elimination": 0
          }
        },
        "allRusher": {
          "focalFaction": "ottomans",
          "focalPolicy": "opportunist",
          "field": "allRusher",
          "games": 300,
          "firstSeed": 1729522056,
          "focalWins": 112,
          "focalWinRate": 0.37333333333333335,
          "focalEliminated": 0,
          "focalElimRate": 0,
          "victoryTypes": {
            "threshold": 72,
            "cap": 152,
            "suddenDeath": 76,
            "elimination": 0
          },
          "medianRounds": 16,
          "meanRounds": 15.396666666666667,
          "capCloseMargin": 20,
          "capCloseMarginRate": 0.06666666666666667,
          "focalWinTypes": {
            "threshold": 15,
            "cap": 21,
            "suddenDeath": 76,
            "elimination": 0
          }
        },
        "allTrader": {
          "focalFaction": "ottomans",
          "focalPolicy": "opportunist",
          "field": "allTrader",
          "games": 300,
          "firstSeed": 1381031350,
          "focalWins": 45,
          "focalWinRate": 0.15,
          "focalEliminated": 0,
          "focalElimRate": 0,
          "victoryTypes": {
            "threshold": 261,
            "cap": 5,
            "suddenDeath": 34,
            "elimination": 0
          },
          "medianRounds": 16,
          "meanRounds": 15.34,
          "capCloseMargin": 4,
          "capCloseMarginRate": 0.013333333333333334,
          "focalWinTypes": {
            "threshold": 11,
            "cap": 0,
            "suddenDeath": 34,
            "elimination": 0
          }
        },
        "allOpportunist": {
          "focalFaction": "ottomans",
          "focalPolicy": "opportunist",
          "field": "allOpportunist",
          "games": 300,
          "firstSeed": 2142803763,
          "focalWins": 60,
          "focalWinRate": 0.2,
          "focalEliminated": 0,
          "focalElimRate": 0,
          "victoryTypes": {
            "threshold": 173,
            "cap": 84,
            "suddenDeath": 43,
            "elimination": 0
          },
          "medianRounds": 16,
          "meanRounds": 14.76,
          "capCloseMargin": 5,
          "capCloseMarginRate": 0.016666666666666666,
          "focalWinTypes": {
            "threshold": 7,
            "cap": 10,
            "suddenDeath": 43,
            "elimination": 0
          }
        }
      }
    },
    "venice": {
      "rusher": {
        "mixed": {
          "focalFaction": "venice",
          "focalPolicy": "rusher",
          "field": "mixed",
          "games": 300,
          "firstSeed": 108718257,
          "focalWins": 2,
          "focalWinRate": 0.006666666666666667,
          "focalEliminated": 0,
          "focalElimRate": 0,
          "victoryTypes": {
            "threshold": 136,
            "cap": 150,
            "suddenDeath": 14,
            "elimination": 0
          },
          "medianRounds": 16,
          "meanRounds": 15.38,
          "capCloseMargin": 16,
          "capCloseMarginRate": 0.05333333333333334,
          "focalWinTypes": {
            "threshold": 0,
            "cap": 2,
            "suddenDeath": 0,
            "elimination": 0
          }
        },
        "allRusher": {
          "focalFaction": "venice",
          "focalPolicy": "rusher",
          "field": "allRusher",
          "games": 300,
          "firstSeed": 210072521,
          "focalWins": 6,
          "focalWinRate": 0.02,
          "focalEliminated": 0,
          "focalElimRate": 0,
          "victoryTypes": {
            "threshold": 72,
            "cap": 146,
            "suddenDeath": 82,
            "elimination": 0
          },
          "medianRounds": 16,
          "meanRounds": 15.55,
          "capCloseMargin": 22,
          "capCloseMarginRate": 0.07333333333333333,
          "focalWinTypes": {
            "threshold": 0,
            "cap": 6,
            "suddenDeath": 0,
            "elimination": 0
          }
        },
        "allTrader": {
          "focalFaction": "venice",
          "focalPolicy": "rusher",
          "field": "allTrader",
          "games": 300,
          "firstSeed": 2037320825,
          "focalWins": 0,
          "focalWinRate": 0,
          "focalEliminated": 0,
          "focalElimRate": 0,
          "victoryTypes": {
            "threshold": 275,
            "cap": 25,
            "suddenDeath": 0,
            "elimination": 0
          },
          "medianRounds": 16,
          "meanRounds": 15.36,
          "capCloseMargin": 4,
          "capCloseMarginRate": 0.013333333333333334,
          "focalWinTypes": {
            "threshold": 0,
            "cap": 0,
            "suddenDeath": 0,
            "elimination": 0
          }
        },
        "allOpportunist": {
          "focalFaction": "venice",
          "focalPolicy": "rusher",
          "field": "allOpportunist",
          "games": 300,
          "firstSeed": 1167373555,
          "focalWins": 3,
          "focalWinRate": 0.01,
          "focalEliminated": 0,
          "focalElimRate": 0,
          "victoryTypes": {
            "threshold": 163,
            "cap": 91,
            "suddenDeath": 46,
            "elimination": 0
          },
          "medianRounds": 16,
          "meanRounds": 14.94,
          "capCloseMargin": 8,
          "capCloseMarginRate": 0.02666666666666667,
          "focalWinTypes": {
            "threshold": 0,
            "cap": 3,
            "suddenDeath": 0,
            "elimination": 0
          }
        }
      },
      "trader": {
        "mixed": {
          "focalFaction": "venice",
          "focalPolicy": "trader",
          "field": "mixed",
          "games": 300,
          "firstSeed": 1254224682,
          "focalWins": 106,
          "focalWinRate": 0.35333333333333333,
          "focalEliminated": 0,
          "focalElimRate": 0,
          "victoryTypes": {
            "threshold": 220,
            "cap": 63,
            "suddenDeath": 17,
            "elimination": 0
          },
          "medianRounds": 16,
          "meanRounds": 15.256666666666666,
          "capCloseMargin": 9,
          "capCloseMarginRate": 0.03,
          "focalWinTypes": {
            "threshold": 90,
            "cap": 16,
            "suddenDeath": 0,
            "elimination": 0
          }
        },
        "allRusher": {
          "focalFaction": "venice",
          "focalPolicy": "trader",
          "field": "allRusher",
          "games": 300,
          "firstSeed": 1711777574,
          "focalWins": 47,
          "focalWinRate": 0.15666666666666668,
          "focalEliminated": 0,
          "focalElimRate": 0,
          "victoryTypes": {
            "threshold": 87,
            "cap": 150,
            "suddenDeath": 63,
            "elimination": 0
          },
          "medianRounds": 16,
          "meanRounds": 15.433333333333334,
          "capCloseMargin": 52,
          "capCloseMarginRate": 0.17333333333333334,
          "focalWinTypes": {
            "threshold": 10,
            "cap": 37,
            "suddenDeath": 0,
            "elimination": 0
          }
        },
        "allTrader": {
          "focalFaction": "venice",
          "focalPolicy": "trader",
          "field": "allTrader",
          "games": 300,
          "firstSeed": 2060881681,
          "focalWins": 150,
          "focalWinRate": 0.5,
          "focalEliminated": 0,
          "focalElimRate": 0,
          "victoryTypes": {
            "threshold": 291,
            "cap": 9,
            "suddenDeath": 0,
            "elimination": 0
          },
          "medianRounds": 16,
          "meanRounds": 15.39,
          "capCloseMargin": 7,
          "capCloseMarginRate": 0.023333333333333334,
          "focalWinTypes": {
            "threshold": 145,
            "cap": 5,
            "suddenDeath": 0,
            "elimination": 0
          }
        },
        "allOpportunist": {
          "focalFaction": "venice",
          "focalPolicy": "trader",
          "field": "allOpportunist",
          "games": 300,
          "firstSeed": 1743223967,
          "focalWins": 14,
          "focalWinRate": 0.04666666666666667,
          "focalEliminated": 0,
          "focalElimRate": 0,
          "victoryTypes": {
            "threshold": 176,
            "cap": 80,
            "suddenDeath": 44,
            "elimination": 0
          },
          "medianRounds": 15,
          "meanRounds": 14.743333333333334,
          "capCloseMargin": 12,
          "capCloseMarginRate": 0.04,
          "focalWinTypes": {
            "threshold": 8,
            "cap": 6,
            "suddenDeath": 0,
            "elimination": 0
          }
        }
      },
      "turtler": {
        "mixed": {
          "focalFaction": "venice",
          "focalPolicy": "turtler",
          "field": "mixed",
          "games": 300,
          "firstSeed": 1148890292,
          "focalWins": 73,
          "focalWinRate": 0.24333333333333335,
          "focalEliminated": 0,
          "focalElimRate": 0,
          "victoryTypes": {
            "threshold": 168,
            "cap": 98,
            "suddenDeath": 34,
            "elimination": 0
          },
          "medianRounds": 16,
          "meanRounds": 15.156666666666666,
          "capCloseMargin": 19,
          "capCloseMarginRate": 0.06333333333333334,
          "focalWinTypes": {
            "threshold": 15,
            "cap": 58,
            "suddenDeath": 0,
            "elimination": 0
          }
        },
        "allRusher": {
          "focalFaction": "venice",
          "focalPolicy": "turtler",
          "field": "allRusher",
          "games": 300,
          "firstSeed": 1617720953,
          "focalWins": 49,
          "focalWinRate": 0.16333333333333333,
          "focalEliminated": 0,
          "focalElimRate": 0,
          "victoryTypes": {
            "threshold": 91,
            "cap": 140,
            "suddenDeath": 69,
            "elimination": 0
          },
          "medianRounds": 16,
          "meanRounds": 15.323333333333334,
          "capCloseMargin": 40,
          "capCloseMarginRate": 0.13333333333333333,
          "focalWinTypes": {
            "threshold": 2,
            "cap": 47,
            "suddenDeath": 0,
            "elimination": 0
          }
        },
        "allTrader": {
          "focalFaction": "venice",
          "focalPolicy": "turtler",
          "field": "allTrader",
          "games": 300,
          "firstSeed": 1103326615,
          "focalWins": 4,
          "focalWinRate": 0.013333333333333334,
          "focalEliminated": 0,
          "focalElimRate": 0,
          "victoryTypes": {
            "threshold": 280,
            "cap": 20,
            "suddenDeath": 0,
            "elimination": 0
          },
          "medianRounds": 16,
          "meanRounds": 15.573333333333334,
          "capCloseMargin": 3,
          "capCloseMarginRate": 0.01,
          "focalWinTypes": {
            "threshold": 3,
            "cap": 1,
            "suddenDeath": 0,
            "elimination": 0
          }
        },
        "allOpportunist": {
          "focalFaction": "venice",
          "focalPolicy": "turtler",
          "field": "allOpportunist",
          "games": 300,
          "firstSeed": 1131931732,
          "focalWins": 9,
          "focalWinRate": 0.03,
          "focalEliminated": 0,
          "focalElimRate": 0,
          "victoryTypes": {
            "threshold": 172,
            "cap": 87,
            "suddenDeath": 41,
            "elimination": 0
          },
          "medianRounds": 16,
          "meanRounds": 14.793333333333333,
          "capCloseMargin": 11,
          "capCloseMarginRate": 0.03666666666666667,
          "focalWinTypes": {
            "threshold": 3,
            "cap": 6,
            "suddenDeath": 0,
            "elimination": 0
          }
        }
      },
      "opportunist": {
        "mixed": {
          "focalFaction": "venice",
          "focalPolicy": "opportunist",
          "field": "mixed",
          "games": 300,
          "firstSeed": 1329766905,
          "focalWins": 0,
          "focalWinRate": 0,
          "focalEliminated": 0,
          "focalElimRate": 0,
          "victoryTypes": {
            "threshold": 134,
            "cap": 146,
            "suddenDeath": 20,
            "elimination": 0
          },
          "medianRounds": 16,
          "meanRounds": 15.31,
          "capCloseMargin": 19,
          "capCloseMarginRate": 0.06333333333333334,
          "focalWinTypes": {
            "threshold": 0,
            "cap": 0,
            "suddenDeath": 0,
            "elimination": 0
          }
        },
        "allRusher": {
          "focalFaction": "venice",
          "focalPolicy": "opportunist",
          "field": "allRusher",
          "games": 300,
          "firstSeed": 802410313,
          "focalWins": 0,
          "focalWinRate": 0,
          "focalEliminated": 0,
          "focalElimRate": 0,
          "victoryTypes": {
            "threshold": 83,
            "cap": 156,
            "suddenDeath": 61,
            "elimination": 0
          },
          "medianRounds": 16,
          "meanRounds": 15.45,
          "capCloseMargin": 19,
          "capCloseMarginRate": 0.06333333333333334,
          "focalWinTypes": {
            "threshold": 0,
            "cap": 0,
            "suddenDeath": 0,
            "elimination": 0
          }
        },
        "allTrader": {
          "focalFaction": "venice",
          "focalPolicy": "opportunist",
          "field": "allTrader",
          "games": 300,
          "firstSeed": 1091989409,
          "focalWins": 0,
          "focalWinRate": 0,
          "focalEliminated": 0,
          "focalElimRate": 0,
          "victoryTypes": {
            "threshold": 281,
            "cap": 19,
            "suddenDeath": 0,
            "elimination": 0
          },
          "medianRounds": 16,
          "meanRounds": 15.356666666666667,
          "capCloseMargin": 1,
          "capCloseMarginRate": 0.0033333333333333335,
          "focalWinTypes": {
            "threshold": 0,
            "cap": 0,
            "suddenDeath": 0,
            "elimination": 0
          }
        },
        "allOpportunist": {
          "focalFaction": "venice",
          "focalPolicy": "opportunist",
          "field": "allOpportunist",
          "games": 300,
          "firstSeed": 1801519173,
          "focalWins": 0,
          "focalWinRate": 0,
          "focalEliminated": 0,
          "focalElimRate": 0,
          "victoryTypes": {
            "threshold": 155,
            "cap": 95,
            "suddenDeath": 50,
            "elimination": 0
          },
          "medianRounds": 16,
          "meanRounds": 14.94,
          "capCloseMargin": 8,
          "capCloseMarginRate": 0.02666666666666667,
          "focalWinTypes": {
            "threshold": 0,
            "cap": 0,
            "suddenDeath": 0,
            "elimination": 0
          }
        }
      }
    },
    "genoa": {
      "rusher": {
        "mixed": {
          "focalFaction": "genoa",
          "focalPolicy": "rusher",
          "field": "mixed",
          "games": 300,
          "firstSeed": 2098985762,
          "focalWins": 1,
          "focalWinRate": 0.0033333333333333335,
          "focalEliminated": 0,
          "focalElimRate": 0,
          "victoryTypes": {
            "threshold": 145,
            "cap": 133,
            "suddenDeath": 22,
            "elimination": 0
          },
          "medianRounds": 16,
          "meanRounds": 15.43,
          "capCloseMargin": 29,
          "capCloseMarginRate": 0.09666666666666666,
          "focalWinTypes": {
            "threshold": 0,
            "cap": 1,
            "suddenDeath": 0,
            "elimination": 0
          }
        },
        "allRusher": {
          "focalFaction": "genoa",
          "focalPolicy": "rusher",
          "field": "allRusher",
          "games": 300,
          "firstSeed": 1834240056,
          "focalWins": 0,
          "focalWinRate": 0,
          "focalEliminated": 0,
          "focalElimRate": 0,
          "victoryTypes": {
            "threshold": 82,
            "cap": 149,
            "suddenDeath": 69,
            "elimination": 0
          },
          "medianRounds": 16,
          "meanRounds": 15.536666666666667,
          "capCloseMargin": 21,
          "capCloseMarginRate": 0.07,
          "focalWinTypes": {
            "threshold": 0,
            "cap": 0,
            "suddenDeath": 0,
            "elimination": 0
          }
        },
        "allTrader": {
          "focalFaction": "genoa",
          "focalPolicy": "rusher",
          "field": "allTrader",
          "games": 300,
          "firstSeed": 126552179,
          "focalWins": 0,
          "focalWinRate": 0,
          "focalEliminated": 0,
          "focalElimRate": 0,
          "victoryTypes": {
            "threshold": 272,
            "cap": 28,
            "suddenDeath": 0,
            "elimination": 0
          },
          "medianRounds": 16,
          "meanRounds": 15.73,
          "capCloseMargin": 2,
          "capCloseMarginRate": 0.006666666666666667,
          "focalWinTypes": {
            "threshold": 0,
            "cap": 0,
            "suddenDeath": 0,
            "elimination": 0
          }
        },
        "allOpportunist": {
          "focalFaction": "genoa",
          "focalPolicy": "rusher",
          "field": "allOpportunist",
          "games": 300,
          "firstSeed": 2009415052,
          "focalWins": 0,
          "focalWinRate": 0,
          "focalEliminated": 0,
          "focalElimRate": 0,
          "victoryTypes": {
            "threshold": 155,
            "cap": 81,
            "suddenDeath": 64,
            "elimination": 0
          },
          "medianRounds": 16,
          "meanRounds": 15.043333333333333,
          "capCloseMargin": 4,
          "capCloseMarginRate": 0.013333333333333334,
          "focalWinTypes": {
            "threshold": 0,
            "cap": 0,
            "suddenDeath": 0,
            "elimination": 0
          }
        }
      },
      "trader": {
        "mixed": {
          "focalFaction": "genoa",
          "focalPolicy": "trader",
          "field": "mixed",
          "games": 300,
          "firstSeed": 1188941176,
          "focalWins": 163,
          "focalWinRate": 0.5433333333333333,
          "focalEliminated": 0,
          "focalElimRate": 0,
          "victoryTypes": {
            "threshold": 242,
            "cap": 35,
            "suddenDeath": 23,
            "elimination": 0
          },
          "medianRounds": 16,
          "meanRounds": 15.083333333333334,
          "capCloseMargin": 5,
          "capCloseMarginRate": 0.016666666666666666,
          "focalWinTypes": {
            "threshold": 146,
            "cap": 17,
            "suddenDeath": 0,
            "elimination": 0
          }
        },
        "allRusher": {
          "focalFaction": "genoa",
          "focalPolicy": "trader",
          "field": "allRusher",
          "games": 300,
          "firstSeed": 698772031,
          "focalWins": 161,
          "focalWinRate": 0.5366666666666666,
          "focalEliminated": 0,
          "focalElimRate": 0,
          "victoryTypes": {
            "threshold": 208,
            "cap": 41,
            "suddenDeath": 51,
            "elimination": 0
          },
          "medianRounds": 16,
          "meanRounds": 15.163333333333334,
          "capCloseMargin": 4,
          "capCloseMarginRate": 0.013333333333333334,
          "focalWinTypes": {
            "threshold": 140,
            "cap": 21,
            "suddenDeath": 0,
            "elimination": 0
          }
        },
        "allTrader": {
          "focalFaction": "genoa",
          "focalPolicy": "trader",
          "field": "allTrader",
          "games": 300,
          "firstSeed": 1627853200,
          "focalWins": 121,
          "focalWinRate": 0.4033333333333333,
          "focalEliminated": 0,
          "focalElimRate": 0,
          "victoryTypes": {
            "threshold": 282,
            "cap": 18,
            "suddenDeath": 0,
            "elimination": 0
          },
          "medianRounds": 16,
          "meanRounds": 15.373333333333333,
          "capCloseMargin": 15,
          "capCloseMarginRate": 0.05,
          "focalWinTypes": {
            "threshold": 118,
            "cap": 3,
            "suddenDeath": 0,
            "elimination": 0
          }
        },
        "allOpportunist": {
          "focalFaction": "genoa",
          "focalPolicy": "trader",
          "field": "allOpportunist",
          "games": 300,
          "firstSeed": 672128171,
          "focalWins": 101,
          "focalWinRate": 0.33666666666666667,
          "focalEliminated": 0,
          "focalElimRate": 0,
          "victoryTypes": {
            "threshold": 240,
            "cap": 23,
            "suddenDeath": 37,
            "elimination": 0
          },
          "medianRounds": 15,
          "meanRounds": 14.653333333333334,
          "capCloseMargin": 3,
          "capCloseMarginRate": 0.01,
          "focalWinTypes": {
            "threshold": 92,
            "cap": 9,
            "suddenDeath": 0,
            "elimination": 0
          }
        }
      },
      "turtler": {
        "mixed": {
          "focalFaction": "genoa",
          "focalPolicy": "turtler",
          "field": "mixed",
          "games": 300,
          "firstSeed": 1395126124,
          "focalWins": 114,
          "focalWinRate": 0.38,
          "focalEliminated": 0,
          "focalElimRate": 0,
          "victoryTypes": {
            "threshold": 152,
            "cap": 122,
            "suddenDeath": 26,
            "elimination": 0
          },
          "medianRounds": 16,
          "meanRounds": 15.26,
          "capCloseMargin": 19,
          "capCloseMarginRate": 0.06333333333333334,
          "focalWinTypes": {
            "threshold": 29,
            "cap": 85,
            "suddenDeath": 0,
            "elimination": 0
          }
        },
        "allRusher": {
          "focalFaction": "genoa",
          "focalPolicy": "turtler",
          "field": "allRusher",
          "games": 300,
          "firstSeed": 1958834309,
          "focalWins": 121,
          "focalWinRate": 0.4033333333333333,
          "focalEliminated": 0,
          "focalElimRate": 0,
          "victoryTypes": {
            "threshold": 106,
            "cap": 129,
            "suddenDeath": 65,
            "elimination": 0
          },
          "medianRounds": 16,
          "meanRounds": 15.326666666666666,
          "capCloseMargin": 20,
          "capCloseMarginRate": 0.06666666666666667,
          "focalWinTypes": {
            "threshold": 25,
            "cap": 96,
            "suddenDeath": 0,
            "elimination": 0
          }
        },
        "allTrader": {
          "focalFaction": "genoa",
          "focalPolicy": "turtler",
          "field": "allTrader",
          "games": 300,
          "firstSeed": 1389232326,
          "focalWins": 17,
          "focalWinRate": 0.056666666666666664,
          "focalEliminated": 0,
          "focalElimRate": 0,
          "victoryTypes": {
            "threshold": 275,
            "cap": 25,
            "suddenDeath": 0,
            "elimination": 0
          },
          "medianRounds": 16,
          "meanRounds": 15.653333333333334,
          "capCloseMargin": 6,
          "capCloseMarginRate": 0.02,
          "focalWinTypes": {
            "threshold": 15,
            "cap": 2,
            "suddenDeath": 0,
            "elimination": 0
          }
        },
        "allOpportunist": {
          "focalFaction": "genoa",
          "focalPolicy": "turtler",
          "field": "allOpportunist",
          "games": 300,
          "firstSeed": 1635661077,
          "focalWins": 68,
          "focalWinRate": 0.22666666666666666,
          "focalEliminated": 0,
          "focalElimRate": 0,
          "victoryTypes": {
            "threshold": 163,
            "cap": 79,
            "suddenDeath": 58,
            "elimination": 0
          },
          "medianRounds": 16,
          "meanRounds": 14.966666666666667,
          "capCloseMargin": 13,
          "capCloseMarginRate": 0.043333333333333335,
          "focalWinTypes": {
            "threshold": 14,
            "cap": 54,
            "suddenDeath": 0,
            "elimination": 0
          }
        }
      },
      "opportunist": {
        "mixed": {
          "focalFaction": "genoa",
          "focalPolicy": "opportunist",
          "field": "mixed",
          "games": 300,
          "firstSeed": 586446574,
          "focalWins": 0,
          "focalWinRate": 0,
          "focalEliminated": 0,
          "focalElimRate": 0,
          "victoryTypes": {
            "threshold": 117,
            "cap": 158,
            "suddenDeath": 25,
            "elimination": 0
          },
          "medianRounds": 16,
          "meanRounds": 15.41,
          "capCloseMargin": 15,
          "capCloseMarginRate": 0.05,
          "focalWinTypes": {
            "threshold": 0,
            "cap": 0,
            "suddenDeath": 0,
            "elimination": 0
          }
        },
        "allRusher": {
          "focalFaction": "genoa",
          "focalPolicy": "opportunist",
          "field": "allRusher",
          "games": 300,
          "firstSeed": 1224844442,
          "focalWins": 0,
          "focalWinRate": 0,
          "focalEliminated": 0,
          "focalElimRate": 0,
          "victoryTypes": {
            "threshold": 76,
            "cap": 147,
            "suddenDeath": 77,
            "elimination": 0
          },
          "medianRounds": 16,
          "meanRounds": 15.363333333333333,
          "capCloseMargin": 31,
          "capCloseMarginRate": 0.10333333333333333,
          "focalWinTypes": {
            "threshold": 0,
            "cap": 0,
            "suddenDeath": 0,
            "elimination": 0
          }
        },
        "allTrader": {
          "focalFaction": "genoa",
          "focalPolicy": "opportunist",
          "field": "allTrader",
          "games": 300,
          "firstSeed": 983348281,
          "focalWins": 0,
          "focalWinRate": 0,
          "focalEliminated": 0,
          "focalElimRate": 0,
          "victoryTypes": {
            "threshold": 268,
            "cap": 32,
            "suddenDeath": 0,
            "elimination": 0
          },
          "medianRounds": 16,
          "meanRounds": 15.71,
          "capCloseMargin": 5,
          "capCloseMarginRate": 0.016666666666666666,
          "focalWinTypes": {
            "threshold": 0,
            "cap": 0,
            "suddenDeath": 0,
            "elimination": 0
          }
        },
        "allOpportunist": {
          "focalFaction": "genoa",
          "focalPolicy": "opportunist",
          "field": "allOpportunist",
          "games": 300,
          "firstSeed": 920956577,
          "focalWins": 0,
          "focalWinRate": 0,
          "focalEliminated": 0,
          "focalElimRate": 0,
          "victoryTypes": {
            "threshold": 168,
            "cap": 78,
            "suddenDeath": 54,
            "elimination": 0
          },
          "medianRounds": 16,
          "meanRounds": 14.916666666666666,
          "capCloseMargin": 3,
          "capCloseMarginRate": 0.01,
          "focalWinTypes": {
            "threshold": 0,
            "cap": 0,
            "suddenDeath": 0,
            "elimination": 0
          }
        }
      }
    },
    "hungary": {
      "rusher": {
        "mixed": {
          "focalFaction": "hungary",
          "focalPolicy": "rusher",
          "field": "mixed",
          "games": 300,
          "firstSeed": 1270244242,
          "focalWins": 64,
          "focalWinRate": 0.21333333333333335,
          "focalEliminated": 0,
          "focalElimRate": 0,
          "victoryTypes": {
            "threshold": 142,
            "cap": 138,
            "suddenDeath": 20,
            "elimination": 0
          },
          "medianRounds": 16,
          "meanRounds": 15.386666666666667,
          "capCloseMargin": 28,
          "capCloseMarginRate": 0.09333333333333334,
          "focalWinTypes": {
            "threshold": 24,
            "cap": 40,
            "suddenDeath": 0,
            "elimination": 0
          }
        },
        "allRusher": {
          "focalFaction": "hungary",
          "focalPolicy": "rusher",
          "field": "allRusher",
          "games": 300,
          "firstSeed": 622897636,
          "focalWins": 114,
          "focalWinRate": 0.38,
          "focalEliminated": 0,
          "focalElimRate": 0,
          "victoryTypes": {
            "threshold": 91,
            "cap": 132,
            "suddenDeath": 77,
            "elimination": 0
          },
          "medianRounds": 16,
          "meanRounds": 15.386666666666667,
          "capCloseMargin": 14,
          "capCloseMarginRate": 0.04666666666666667,
          "focalWinTypes": {
            "threshold": 39,
            "cap": 75,
            "suddenDeath": 0,
            "elimination": 0
          }
        },
        "allTrader": {
          "focalFaction": "hungary",
          "focalPolicy": "rusher",
          "field": "allTrader",
          "games": 300,
          "firstSeed": 1659999502,
          "focalWins": 18,
          "focalWinRate": 0.06,
          "focalEliminated": 0,
          "focalElimRate": 0,
          "victoryTypes": {
            "threshold": 274,
            "cap": 26,
            "suddenDeath": 0,
            "elimination": 0
          },
          "medianRounds": 16,
          "meanRounds": 15.21,
          "capCloseMargin": 1,
          "capCloseMarginRate": 0.0033333333333333335,
          "focalWinTypes": {
            "threshold": 18,
            "cap": 0,
            "suddenDeath": 0,
            "elimination": 0
          }
        },
        "allOpportunist": {
          "focalFaction": "hungary",
          "focalPolicy": "rusher",
          "field": "allOpportunist",
          "games": 300,
          "firstSeed": 987033917,
          "focalWins": 135,
          "focalWinRate": 0.45,
          "focalEliminated": 0,
          "focalElimRate": 0,
          "victoryTypes": {
            "threshold": 85,
            "cap": 151,
            "suddenDeath": 64,
            "elimination": 0
          },
          "medianRounds": 16,
          "meanRounds": 15.276666666666667,
          "capCloseMargin": 13,
          "capCloseMarginRate": 0.043333333333333335,
          "focalWinTypes": {
            "threshold": 25,
            "cap": 110,
            "suddenDeath": 0,
            "elimination": 0
          }
        }
      },
      "trader": {
        "mixed": {
          "focalFaction": "hungary",
          "focalPolicy": "trader",
          "field": "mixed",
          "games": 300,
          "firstSeed": 894637858,
          "focalWins": 34,
          "focalWinRate": 0.11333333333333333,
          "focalEliminated": 0,
          "focalElimRate": 0,
          "victoryTypes": {
            "threshold": 171,
            "cap": 104,
            "suddenDeath": 25,
            "elimination": 0
          },
          "medianRounds": 16,
          "meanRounds": 15.51,
          "capCloseMargin": 14,
          "capCloseMarginRate": 0.04666666666666667,
          "focalWinTypes": {
            "threshold": 16,
            "cap": 18,
            "suddenDeath": 0,
            "elimination": 0
          }
        },
        "allRusher": {
          "focalFaction": "hungary",
          "focalPolicy": "trader",
          "field": "allRusher",
          "games": 300,
          "firstSeed": 662842036,
          "focalWins": 100,
          "focalWinRate": 0.3333333333333333,
          "focalEliminated": 0,
          "focalElimRate": 0,
          "victoryTypes": {
            "threshold": 76,
            "cap": 138,
            "suddenDeath": 86,
            "elimination": 0
          },
          "medianRounds": 16,
          "meanRounds": 15.62,
          "capCloseMargin": 24,
          "capCloseMarginRate": 0.08,
          "focalWinTypes": {
            "threshold": 14,
            "cap": 86,
            "suddenDeath": 0,
            "elimination": 0
          }
        },
        "allTrader": {
          "focalFaction": "hungary",
          "focalPolicy": "trader",
          "field": "allTrader",
          "games": 300,
          "firstSeed": 1063211091,
          "focalWins": 4,
          "focalWinRate": 0.013333333333333334,
          "focalEliminated": 0,
          "focalElimRate": 0,
          "victoryTypes": {
            "threshold": 286,
            "cap": 14,
            "suddenDeath": 0,
            "elimination": 0
          },
          "medianRounds": 16,
          "meanRounds": 15.296666666666667,
          "capCloseMargin": 9,
          "capCloseMarginRate": 0.03,
          "focalWinTypes": {
            "threshold": 4,
            "cap": 0,
            "suddenDeath": 0,
            "elimination": 0
          }
        },
        "allOpportunist": {
          "focalFaction": "hungary",
          "focalPolicy": "trader",
          "field": "allOpportunist",
          "games": 300,
          "firstSeed": 693487946,
          "focalWins": 123,
          "focalWinRate": 0.41,
          "focalEliminated": 0,
          "focalElimRate": 0,
          "victoryTypes": {
            "threshold": 87,
            "cap": 135,
            "suddenDeath": 78,
            "elimination": 0
          },
          "medianRounds": 16,
          "meanRounds": 15.333333333333334,
          "capCloseMargin": 10,
          "capCloseMarginRate": 0.03333333333333333,
          "focalWinTypes": {
            "threshold": 12,
            "cap": 111,
            "suddenDeath": 0,
            "elimination": 0
          }
        }
      },
      "turtler": {
        "mixed": {
          "focalFaction": "hungary",
          "focalPolicy": "turtler",
          "field": "mixed",
          "games": 300,
          "firstSeed": 2097167906,
          "focalWins": 32,
          "focalWinRate": 0.10666666666666667,
          "focalEliminated": 0,
          "focalElimRate": 0,
          "victoryTypes": {
            "threshold": 148,
            "cap": 125,
            "suddenDeath": 27,
            "elimination": 0
          },
          "medianRounds": 16,
          "meanRounds": 15.506666666666666,
          "capCloseMargin": 25,
          "capCloseMarginRate": 0.08333333333333333,
          "focalWinTypes": {
            "threshold": 5,
            "cap": 27,
            "suddenDeath": 0,
            "elimination": 0
          }
        },
        "allRusher": {
          "focalFaction": "hungary",
          "focalPolicy": "turtler",
          "field": "allRusher",
          "games": 300,
          "firstSeed": 1823156574,
          "focalWins": 92,
          "focalWinRate": 0.30666666666666664,
          "focalEliminated": 0,
          "focalElimRate": 0,
          "victoryTypes": {
            "threshold": 53,
            "cap": 160,
            "suddenDeath": 87,
            "elimination": 0
          },
          "medianRounds": 16,
          "meanRounds": 15.746666666666666,
          "capCloseMargin": 34,
          "capCloseMarginRate": 0.11333333333333333,
          "focalWinTypes": {
            "threshold": 6,
            "cap": 86,
            "suddenDeath": 0,
            "elimination": 0
          }
        },
        "allTrader": {
          "focalFaction": "hungary",
          "focalPolicy": "turtler",
          "field": "allTrader",
          "games": 300,
          "firstSeed": 1148364439,
          "focalWins": 4,
          "focalWinRate": 0.013333333333333334,
          "focalEliminated": 0,
          "focalElimRate": 0,
          "victoryTypes": {
            "threshold": 291,
            "cap": 9,
            "suddenDeath": 0,
            "elimination": 0
          },
          "medianRounds": 16,
          "meanRounds": 15.343333333333334,
          "capCloseMargin": 8,
          "capCloseMarginRate": 0.02666666666666667,
          "focalWinTypes": {
            "threshold": 4,
            "cap": 0,
            "suddenDeath": 0,
            "elimination": 0
          }
        },
        "allOpportunist": {
          "focalFaction": "hungary",
          "focalPolicy": "turtler",
          "field": "allOpportunist",
          "games": 300,
          "firstSeed": 1468494976,
          "focalWins": 145,
          "focalWinRate": 0.48333333333333334,
          "focalEliminated": 0,
          "focalElimRate": 0,
          "victoryTypes": {
            "threshold": 76,
            "cap": 158,
            "suddenDeath": 66,
            "elimination": 0
          },
          "medianRounds": 16,
          "meanRounds": 15.453333333333333,
          "capCloseMargin": 15,
          "capCloseMarginRate": 0.05,
          "focalWinTypes": {
            "threshold": 13,
            "cap": 132,
            "suddenDeath": 0,
            "elimination": 0
          }
        }
      },
      "opportunist": {
        "mixed": {
          "focalFaction": "hungary",
          "focalPolicy": "opportunist",
          "field": "mixed",
          "games": 300,
          "firstSeed": 523583732,
          "focalWins": 162,
          "focalWinRate": 0.54,
          "focalEliminated": 0,
          "focalElimRate": 0,
          "victoryTypes": {
            "threshold": 202,
            "cap": 89,
            "suddenDeath": 9,
            "elimination": 0
          },
          "medianRounds": 15,
          "meanRounds": 14.933333333333334,
          "capCloseMargin": 19,
          "capCloseMarginRate": 0.06333333333333334,
          "focalWinTypes": {
            "threshold": 122,
            "cap": 40,
            "suddenDeath": 0,
            "elimination": 0
          }
        },
        "allRusher": {
          "focalFaction": "hungary",
          "focalPolicy": "opportunist",
          "field": "allRusher",
          "games": 300,
          "firstSeed": 1984625640,
          "focalWins": 171,
          "focalWinRate": 0.57,
          "focalEliminated": 0,
          "focalElimRate": 0,
          "victoryTypes": {
            "threshold": 150,
            "cap": 97,
            "suddenDeath": 53,
            "elimination": 0
          },
          "medianRounds": 16,
          "meanRounds": 15.146666666666667,
          "capCloseMargin": 7,
          "capCloseMarginRate": 0.023333333333333334,
          "focalWinTypes": {
            "threshold": 96,
            "cap": 75,
            "suddenDeath": 0,
            "elimination": 0
          }
        },
        "allTrader": {
          "focalFaction": "hungary",
          "focalPolicy": "opportunist",
          "field": "allTrader",
          "games": 300,
          "firstSeed": 1517560890,
          "focalWins": 111,
          "focalWinRate": 0.37,
          "focalEliminated": 0,
          "focalElimRate": 0,
          "victoryTypes": {
            "threshold": 289,
            "cap": 11,
            "suddenDeath": 0,
            "elimination": 0
          },
          "medianRounds": 15,
          "meanRounds": 14.743333333333334,
          "capCloseMargin": 2,
          "capCloseMarginRate": 0.006666666666666667,
          "focalWinTypes": {
            "threshold": 111,
            "cap": 0,
            "suddenDeath": 0,
            "elimination": 0
          }
        },
        "allOpportunist": {
          "focalFaction": "hungary",
          "focalPolicy": "opportunist",
          "field": "allOpportunist",
          "games": 300,
          "firstSeed": 2053046844,
          "focalWins": 170,
          "focalWinRate": 0.5666666666666667,
          "focalEliminated": 0,
          "focalElimRate": 0,
          "victoryTypes": {
            "threshold": 174,
            "cap": 78,
            "suddenDeath": 48,
            "elimination": 0
          },
          "medianRounds": 16,
          "meanRounds": 14.76,
          "capCloseMargin": 5,
          "capCloseMarginRate": 0.016666666666666666,
          "focalWinTypes": {
            "threshold": 103,
            "cap": 67,
            "suddenDeath": 0,
            "elimination": 0
          }
        }
      }
    }
  },
  "extremes": [
    {
      "policy": "rusher",
      "games": 1000,
      "firstSeed": 97284472,
      "medianRounds": 16,
      "meanRounds": 15.477,
      "earlyEndRate": 0.012,
      "victoryTypes": {
        "threshold": 248,
        "cap": 518,
        "suddenDeath": 234,
        "elimination": 0
      },
      "victoryRates": {
        "threshold": 0.248,
        "cap": 0.518,
        "suddenDeath": 0.234,
        "elimination": 0
      },
      "capCloseMargin": 70,
      "capCloseMarginRate": 0.07,
      "winsByFaction": {
        "byzantium": 116,
        "ottomans": 500,
        "venice": 16,
        "genoa": 1,
        "hungary": 367
      }
    },
    {
      "policy": "trader",
      "games": 1000,
      "firstSeed": 1544501420,
      "medianRounds": 16,
      "meanRounds": 15.37,
      "earlyEndRate": 0,
      "victoryTypes": {
        "threshold": 968,
        "cap": 32,
        "suddenDeath": 0,
        "elimination": 0
      },
      "victoryRates": {
        "threshold": 0.968,
        "cap": 0.032,
        "suddenDeath": 0,
        "elimination": 0
      },
      "capCloseMargin": 27,
      "capCloseMarginRate": 0.027,
      "winsByFaction": {
        "byzantium": 63,
        "ottomans": 0,
        "venice": 536,
        "genoa": 382,
        "hungary": 19
      }
    },
    {
      "policy": "turtler",
      "games": 1000,
      "firstSeed": 594372764,
      "medianRounds": 16,
      "meanRounds": 15.89,
      "earlyEndRate": 0,
      "victoryTypes": {
        "threshold": 349,
        "cap": 651,
        "suddenDeath": 0,
        "elimination": 0
      },
      "victoryRates": {
        "threshold": 0.349,
        "cap": 0.651,
        "suddenDeath": 0,
        "elimination": 0
      },
      "capCloseMargin": 453,
      "capCloseMarginRate": 0.453,
      "winsByFaction": {
        "byzantium": 134,
        "ottomans": 0,
        "venice": 538,
        "genoa": 293,
        "hungary": 35
      }
    },
    {
      "policy": "opportunist",
      "games": 1000,
      "firstSeed": 1778696278,
      "medianRounds": 16,
      "meanRounds": 14.951,
      "earlyEndRate": 0.028,
      "victoryTypes": {
        "threshold": 539,
        "cap": 280,
        "suddenDeath": 181,
        "elimination": 0
      },
      "victoryRates": {
        "threshold": 0.539,
        "cap": 0.28,
        "suddenDeath": 0.181,
        "elimination": 0
      },
      "capCloseMargin": 15,
      "capCloseMarginRate": 0.015,
      "winsByFaction": {
        "byzantium": 188,
        "ottomans": 228,
        "venice": 0,
        "genoa": 0,
        "hungary": 584
      }
    }
  ],
  "flags": [
    {
      "kind": "floor",
      "detail": "byzantium+trader vs allTrader: 4.3% (13/300, elim 0.0%)"
    },
    {
      "kind": "floor",
      "detail": "byzantium+turtler vs allTrader: 3.3% (10/300, elim 0.0%)"
    },
    {
      "kind": "floor",
      "detail": "ottomans+trader vs mixed: 1.3% (4/300, elim 0.0%)"
    },
    {
      "kind": "floor",
      "detail": "ottomans+trader vs allTrader: 0.0% (0/300, elim 0.0%)"
    },
    {
      "kind": "floor",
      "detail": "ottomans+trader vs allOpportunist: 3.7% (11/300, elim 0.0%)"
    },
    {
      "kind": "floor",
      "detail": "ottomans+turtler vs mixed: 0.0% (0/300, elim 0.0%)"
    },
    {
      "kind": "floor",
      "detail": "ottomans+turtler vs allRusher: 0.0% (0/300, elim 0.0%)"
    },
    {
      "kind": "floor",
      "detail": "ottomans+turtler vs allTrader: 0.0% (0/300, elim 0.0%)"
    },
    {
      "kind": "floor",
      "detail": "ottomans+turtler vs allOpportunist: 0.0% (0/300, elim 0.0%)"
    },
    {
      "kind": "floor",
      "detail": "venice+rusher vs mixed: 0.7% (2/300, elim 0.0%)"
    },
    {
      "kind": "floor",
      "detail": "venice+rusher vs allRusher: 2.0% (6/300, elim 0.0%)"
    },
    {
      "kind": "floor",
      "detail": "venice+rusher vs allTrader: 0.0% (0/300, elim 0.0%)"
    },
    {
      "kind": "floor",
      "detail": "venice+rusher vs allOpportunist: 1.0% (3/300, elim 0.0%)"
    },
    {
      "kind": "floor",
      "detail": "venice+trader vs allOpportunist: 4.7% (14/300, elim 0.0%)"
    },
    {
      "kind": "floor",
      "detail": "venice+turtler vs allTrader: 1.3% (4/300, elim 0.0%)"
    },
    {
      "kind": "floor",
      "detail": "venice+turtler vs allOpportunist: 3.0% (9/300, elim 0.0%)"
    },
    {
      "kind": "floor",
      "detail": "venice+opportunist vs mixed: 0.0% (0/300, elim 0.0%)"
    },
    {
      "kind": "floor",
      "detail": "venice+opportunist vs allRusher: 0.0% (0/300, elim 0.0%)"
    },
    {
      "kind": "floor",
      "detail": "venice+opportunist vs allTrader: 0.0% (0/300, elim 0.0%)"
    },
    {
      "kind": "floor",
      "detail": "venice+opportunist vs allOpportunist: 0.0% (0/300, elim 0.0%)"
    },
    {
      "kind": "floor",
      "detail": "genoa+rusher vs mixed: 0.3% (1/300, elim 0.0%)"
    },
    {
      "kind": "floor",
      "detail": "genoa+rusher vs allRusher: 0.0% (0/300, elim 0.0%)"
    },
    {
      "kind": "floor",
      "detail": "genoa+rusher vs allTrader: 0.0% (0/300, elim 0.0%)"
    },
    {
      "kind": "floor",
      "detail": "genoa+rusher vs allOpportunist: 0.0% (0/300, elim 0.0%)"
    },
    {
      "kind": "floor",
      "detail": "genoa+opportunist vs mixed: 0.0% (0/300, elim 0.0%)"
    },
    {
      "kind": "floor",
      "detail": "genoa+opportunist vs allRusher: 0.0% (0/300, elim 0.0%)"
    },
    {
      "kind": "floor",
      "detail": "genoa+opportunist vs allTrader: 0.0% (0/300, elim 0.0%)"
    },
    {
      "kind": "floor",
      "detail": "genoa+opportunist vs allOpportunist: 0.0% (0/300, elim 0.0%)"
    },
    {
      "kind": "floor",
      "detail": "hungary+trader vs allTrader: 1.3% (4/300, elim 0.0%)"
    },
    {
      "kind": "floor",
      "detail": "hungary+turtler vs allTrader: 1.3% (4/300, elim 0.0%)"
    },
    {
      "kind": "ending",
      "detail": "all-5-turtler: 45.3% of games are cap tiebreaks with margin<2"
    }
  ]
}
