{
  "config": {
    "baseSeed": 111001,
    "gamesPerFactionPerVariant": 1000,
    "variants": [
      "cycle",
      "honest",
      "control"
    ],
    "smoke": false,
    "elapsedMs": 30155,
    "seedScheme": "seed = 111001 + factionIdx*100000 + i, identical across variants (paired)",
    "opponents": "other four factions run rusher/trader/turtler/opportunist (one each, seeded shuffle fork(97))"
  },
  "overall": {
    "cycle": {
      "games": 5000,
      "wins": 1134,
      "rate": 0.2268
    },
    "honest": {
      "games": 5000,
      "wins": 1234,
      "rate": 0.2468
    },
    "control": {
      "games": 5000,
      "wins": 1178,
      "rate": 0.2356
    }
  },
  "byVariantFaction": {
    "cycle": {
      "byzantium": {
        "games": 1000,
        "wins": 351,
        "rate": 0.351,
        "fieldAvgOtherSeats": 0.16225,
        "ratioVsField": 2.163328197226502,
        "winTypes": {
          "threshold": 208,
          "cap": 143,
          "suddenDeath": 0,
          "elimination": 0
        },
        "suddenDeathWinRate": 0,
        "eliminatedRate": 0,
        "avgElimRound": null,
        "avgRounds": 14.934,
        "avgFinalPrestige": 58.97890000000014
      },
      "ottomans": {
        "games": 1000,
        "wins": 279,
        "rate": 0.279,
        "fieldAvgOtherSeats": 0.18025,
        "ratioVsField": 1.547850208044383,
        "winTypes": {
          "threshold": 208,
          "cap": 31,
          "suddenDeath": 40,
          "elimination": 0
        },
        "suddenDeathWinRate": 0.04,
        "eliminatedRate": 0,
        "avgElimRound": null,
        "avgRounds": 14.628,
        "avgFinalPrestige": 49.67070000000005
      },
      "venice": {
        "games": 1000,
        "wins": 150,
        "rate": 0.15,
        "fieldAvgOtherSeats": 0.2125,
        "ratioVsField": 0.7058823529411765,
        "winTypes": {
          "threshold": 24,
          "cap": 126,
          "suddenDeath": 0,
          "elimination": 0
        },
        "suddenDeathWinRate": 0,
        "eliminatedRate": 0,
        "avgElimRound": null,
        "avgRounds": 15.089,
        "avgFinalPrestige": 49.67229999999999
      },
      "genoa": {
        "games": 1000,
        "wins": 133,
        "rate": 0.133,
        "fieldAvgOtherSeats": 0.21675,
        "ratioVsField": 0.6136101499423299,
        "winTypes": {
          "threshold": 8,
          "cap": 125,
          "suddenDeath": 0,
          "elimination": 0
        },
        "suddenDeathWinRate": 0,
        "eliminatedRate": 0,
        "avgElimRound": null,
        "avgRounds": 15.272,
        "avgFinalPrestige": 50.37639999999995
      },
      "hungary": {
        "games": 1000,
        "wins": 221,
        "rate": 0.221,
        "fieldAvgOtherSeats": 0.19475,
        "ratioVsField": 1.134788189987163,
        "winTypes": {
          "threshold": 85,
          "cap": 136,
          "suddenDeath": 0,
          "elimination": 0
        },
        "suddenDeathWinRate": 0,
        "eliminatedRate": 0,
        "avgElimRound": null,
        "avgRounds": 15.14,
        "avgFinalPrestige": 53.1509999999999
      }
    },
    "honest": {
      "byzantium": {
        "games": 1000,
        "wins": 417,
        "rate": 0.417,
        "fieldAvgOtherSeats": 0.14575,
        "ratioVsField": 2.86106346483705,
        "winTypes": {
          "threshold": 296,
          "cap": 121,
          "suddenDeath": 0,
          "elimination": 0
        },
        "suddenDeathWinRate": 0,
        "eliminatedRate": 0,
        "avgElimRound": null,
        "avgRounds": 14.879,
        "avgFinalPrestige": 58.352499999999964
      },
      "ottomans": {
        "games": 1000,
        "wins": 282,
        "rate": 0.282,
        "fieldAvgOtherSeats": 0.1795,
        "ratioVsField": 1.5710306406685235,
        "winTypes": {
          "threshold": 209,
          "cap": 31,
          "suddenDeath": 42,
          "elimination": 0
        },
        "suddenDeathWinRate": 0.042,
        "eliminatedRate": 0,
        "avgElimRound": null,
        "avgRounds": 14.619,
        "avgFinalPrestige": 49.67560000000007
      },
      "venice": {
        "games": 1000,
        "wins": 154,
        "rate": 0.154,
        "fieldAvgOtherSeats": 0.2115,
        "ratioVsField": 0.7281323877068558,
        "winTypes": {
          "threshold": 59,
          "cap": 95,
          "suddenDeath": 0,
          "elimination": 0
        },
        "suddenDeathWinRate": 0,
        "eliminatedRate": 0,
        "avgElimRound": null,
        "avgRounds": 14.976,
        "avgFinalPrestige": 48.50970000000001
      },
      "genoa": {
        "games": 1000,
        "wins": 159,
        "rate": 0.159,
        "fieldAvgOtherSeats": 0.21025,
        "ratioVsField": 0.7562425683709869,
        "winTypes": {
          "threshold": 17,
          "cap": 142,
          "suddenDeath": 0,
          "elimination": 0
        },
        "suddenDeathWinRate": 0,
        "eliminatedRate": 0,
        "avgElimRound": null,
        "avgRounds": 15.262,
        "avgFinalPrestige": 50.39889999999991
      },
      "hungary": {
        "games": 1000,
        "wins": 222,
        "rate": 0.222,
        "fieldAvgOtherSeats": 0.1945,
        "ratioVsField": 1.141388174807198,
        "winTypes": {
          "threshold": 88,
          "cap": 134,
          "suddenDeath": 0,
          "elimination": 0
        },
        "suddenDeathWinRate": 0,
        "eliminatedRate": 0,
        "avgElimRound": null,
        "avgRounds": 15.149,
        "avgFinalPrestige": 53.26439999999991
      }
    },
    "control": {
      "byzantium": {
        "games": 1000,
        "wins": 447,
        "rate": 0.447,
        "fieldAvgOtherSeats": 0.13824999999999998,
        "ratioVsField": 3.2332730560578664,
        "winTypes": {
          "threshold": 320,
          "cap": 127,
          "suddenDeath": 0,
          "elimination": 0
        },
        "suddenDeathWinRate": 0,
        "eliminatedRate": 0,
        "avgElimRound": null,
        "avgRounds": 14.813,
        "avgFinalPrestige": 60.3476000000001
      },
      "ottomans": {
        "games": 1000,
        "wins": 193,
        "rate": 0.193,
        "fieldAvgOtherSeats": 0.20174999999999998,
        "ratioVsField": 0.9566294919454772,
        "winTypes": {
          "threshold": 2,
          "cap": 0,
          "suddenDeath": 191,
          "elimination": 0
        },
        "suddenDeathWinRate": 0.191,
        "eliminatedRate": 0.001,
        "avgElimRound": 10,
        "avgRounds": 15.019,
        "avgFinalPrestige": 29.077200000000055
      },
      "venice": {
        "games": 1000,
        "wins": 169,
        "rate": 0.169,
        "fieldAvgOtherSeats": 0.20775,
        "ratioVsField": 0.8134777376654634,
        "winTypes": {
          "threshold": 24,
          "cap": 145,
          "suddenDeath": 0,
          "elimination": 0
        },
        "suddenDeathWinRate": 0,
        "eliminatedRate": 0,
        "avgElimRound": null,
        "avgRounds": 15.183,
        "avgFinalPrestige": 51.14360000000036
      },
      "genoa": {
        "games": 1000,
        "wins": 81,
        "rate": 0.081,
        "fieldAvgOtherSeats": 0.22975,
        "ratioVsField": 0.352557127312296,
        "winTypes": {
          "threshold": 0,
          "cap": 81,
          "suddenDeath": 0,
          "elimination": 0
        },
        "suddenDeathWinRate": 0,
        "eliminatedRate": 0,
        "avgElimRound": null,
        "avgRounds": 15.225,
        "avgFinalPrestige": 50.43990000000044
      },
      "hungary": {
        "games": 1000,
        "wins": 288,
        "rate": 0.288,
        "fieldAvgOtherSeats": 0.178,
        "ratioVsField": 1.6179775280898876,
        "winTypes": {
          "threshold": 156,
          "cap": 131,
          "suddenDeath": 1,
          "elimination": 0
        },
        "suddenDeathWinRate": 0.001,
        "eliminatedRate": 0.003,
        "avgElimRound": 9.666666666666666,
        "avgRounds": 14.975,
        "avgFinalPrestige": 55.30539999999965
      }
    }
  },
  "pairedCycleVsHonest": {
    "n": 5000,
    "cycleWinsHonestLoses": 277,
    "honestWinsCycleLoses": 377,
    "bothWin": 857,
    "neitherWin": 3489
  },
  "opponentPolicyWinsVsCycle": {
    "rusher": 1165,
    "trader": 1697,
    "turtler": 497,
    "opportunist": 507
  },
  "exploitThresholds": {
    "singleFactionAbove40pct": "flagged below if any",
    "beatsFieldAvgBy2x": "p > 2*(1-p)/4 i.e. p > 33.33%"
  },
  "exploitFlags": [
    "merc-rush(cycle) as byzantium: 35.1% beats field avg by >2x",
    "merc-rush(honest) as byzantium: 41.7% > 40%"
  ]
}
